bth/__init__.py
bth/cli.py
bth/db.py
bth-0.1.1.dist-info/LICENSE
bth-0.1.1.dist-info/METADATA
bth-0.1.1.dist-info/WHEEL
bth-0.1.1.dist-info/entry_points.txt
bth-0.1.1.dist-info/top_level.txt
bth-0.1.1.dist-info/RECORD
