Metadata-Version: 2.1
Name: bth
Version: 0.1.1
Summary: Time tracker for your hourly freelance projects(or just a time tracker for your projects)
Home-page: https://github.com/meetmangukiya/bth-py
Author: Meet Mangukiya
Author-email: meetmangukiya98@gmail.com
License: MIT
Platform: UNKNOWN
Classifier: License :: OSI Approved :: MIT License
Classifier: Programming Language :: Python
Classifier: Programming Language :: Python :: 3
Classifier: Programming Language :: Python :: 3.6
Classifier: Programming Language :: Python :: Implementation :: CPython
Classifier: Programming Language :: Python :: Implementation :: PyPy
Requires-Python: >=3.6.0
Requires-Dist: click
